greedy_boruta/GreedyBoruta.py
greedy_boruta/__init__.py
greedy_boruta/examples/test_y.csv
greedyboruta-0.1.4.dist-info/licenses/LICENSE
greedyboruta-0.1.4.dist-info/METADATA
greedyboruta-0.1.4.dist-info/WHEEL
greedyboruta-0.1.4.dist-info/top_level.txt
greedyboruta-0.1.4.dist-info/RECORD
