Metadata-Version: 2.4
Name: greedyboruta
Version: 0.1.4
Summary: Python Implementation of GreedyBoruta Feature Selection
Home-page: https://github.com/Nicolas-Vana/GreedyBorutaPy
Download-URL: https://github.com/Nicolas-Vana/GreedyBorutaPy/tarball/0.1.5
Author: Nicolas Vana Santos
Author-email: nicolas.vana@gmail.com
License: BSD 3 clause
Keywords: feature selection,machine learning,random forest
License-File: LICENSE
Requires-Dist: numpy>=1.10.4
Requires-Dist: scikit-learn>=0.17.1
Requires-Dist: scipy>=0.17.0
Dynamic: author
Dynamic: author-email
Dynamic: description
Dynamic: description-content-type
Dynamic: download-url
Dynamic: home-page
Dynamic: keywords
Dynamic: license
Dynamic: license-file
Dynamic: requires-dist
Dynamic: summary
